pyDataFitting/__init__.py
pyDataFitting/linear_regression.py
pyDataFitting/model_diagnostics.py
pyDataFitting/model_tools.py
pyDataFitting/nonlinear_regression.py
pyDataFitting/partial_least_squares_regression.py
pyDataFitting/polynomial_regression.py
pyDataFitting/principle_component_regression.py
pydatafitting-0.0.6.dist-info/licenses/LICENSE
pydatafitting-0.0.6.dist-info/METADATA
pydatafitting-0.0.6.dist-info/WHEEL
pydatafitting-0.0.6.dist-info/top_level.txt
pydatafitting-0.0.6.dist-info/RECORD
