Metadata-Version: 2.4
Name: pyDataFitting
Version: 0.0.6
Summary: package for specialized regression
Home-page: https://github.com/AlexanderSouthan/pyDataFitting
Author: Alexander Southan
Author-email: 72788772+AlexanderSouthan@users.noreply.github.com
Project-URL: Bug Tracker, https://github.com/AlexanderSouthan/pyDataFitting/issues
Classifier: Programming Language :: Python :: 3
Classifier: License :: OSI Approved :: MIT License
Classifier: Operating System :: OS Independent
Requires-Python: >=3.6
License-File: LICENSE
Requires-Dist: numpy
Requires-Dist: pandas
Requires-Dist: scipy
Requires-Dist: matplotlib
Requires-Dist: scikit-learn
Requires-Dist: statsmodels
Requires-Dist: lmfit
Requires-Dist: little_helpers
Dynamic: license-file
Dynamic: requires-dist
